{
    "dataId": "01367",
    "company": {
        "name": "Hanbo",
        "stockCode": "01367"
    },
    "esgreport": {
        "h23304a11": {
            "a11": {
                "sox": [],
                "nox": [],
                "pmx": []
            },
            "a15": true
        },
        "h23301a12": {
            "a12": {
                "ghg": [
                    { "2021-01": 3545 },
                    { "2021-02": 3546 },
                    { "2021-03": 3547 },
                    { "2021-04": 3548 },
                    { "2021-05": 3549 },
                    { "2021-06": 3550 },
                    { "2021-07": 3551 },
                    { "2021-08": 3552 },
                    { "2021-09": 3553 },
                    { "2021-10": 3554 },
                    { "2021-11": 3555 },
                    { "2021-12": 3556 }
                ]
            }
        },
        "h23304a13": {
            "a13": {
                "hazardousProduce": []
            },
            "a16": true
        },
        "h23304a14": {
            "a14": {
                "nonHazardousProduce": []
            },
            "a17": true
        },
        "h23303a21": {
            "a21": {
                "electricity": [
                    { "2021-01": 3545 },
                    { "2021-02": 3546 },
                    { "2021-03": 3547 },
                    { "2021-04": 3548 },
                    { "2021-05": 3549 },
                    { "2021-06": 3550 },
                    { "2021-07": 3551 },
                    { "2021-08": 3552 },
                    { "2021-09": 3553 },
                    { "2021-10": 3554 },
                    { "2021-11": 3555 },
                    { "2021-12": 3556 }
                ]
            },
            "a23": true
        },
        "h23303a22": {
            "a22": {
                "water": [
                    { "2021-01": 3545 },
                    { "2021-02": 3546 },
                    { "2021-03": 3547 },
                    { "2021-04": 3548 },
                    { "2021-05": 3549 },
                    { "2021-06": 3550 },
                    { "2021-07": 3551 },
                    { "2021-08": 3552 },
                    { "2021-09": 3553 },
                    { "2021-10": 3554 },
                    { "2021-11": 3555 },
                    { "2021-12": 3556 }
                ]
            },
            "a24": true
        },
        "h23304a25": {
            "a25": {
                "packagingMaterial": []
            }
        },
        "h23303a31": {
            "a31": true
        },
        "h23301a41": {
            "a41": true
        },
        "h23301b11": {
            "b11": {
                "gender": {
                    "m": "60%",
                    "f": "40%"
                },
                "ageGroup": {
                    "1": "20%",
                    "2": "20%",
                    "3": "20%",
                    "4": "20%",
                    "5": "20%"
                },
                "region": {
                    "1": "20%",
                    "2": "20%",
                    "3": "10%",
                    "4": "20%",
                    "5": "0",
                    "6": "10%",
                    "7": "20%",
                    "8": "20%",
                    "9": "0",
                    "10": "0",
                    "11": "0"
                }
            },
            "b12": {
                "gender": {
                    "m": "5%",
                    "f": "3%"
                },
                "ageGroup": {
                    "1": "1%",
                    "2": "1%",
                    "3": "1%",
                    "4": "2%",
                    "5": "2%"
                },
                "region": {
                    "1": "2%",
                    "2": "2%",
                    "3": "1%",
                    "4": "2%",
                    "5": "0",
                    "6": "1%",
                    "7": "2%",
                    "8": "2%",
                    "9": "0",
                    "10": "0",
                    "11": "0"
                }
            }
        },
        "h23303b21": {
            "b21": "2000",
            "b22": "30",
            "b23": true
        },
        "h23305b31": {
            "b31": {
                "male": "78%",
                "female": "72%"
            },
            "b32": {
                "male": "120",
                "female": "120"
            }
        },
        "h23301b41": {
            "b41": true,
            "b42": true
        },
        "h23303b51": {
            "b51": {
                "1": "60",
                "2": "46",
                "3": "10",
                "4": "18",
                "7": "6"
            },
            "b52": true
        },
        "h23303b61": {
            "b61": "2%",
            "b62": "15",
            "b63": true,
            "b64": true,
            "b65": true
        },
        "h23301b71": {
            "b71": "1",
            "b72": true
        },
        "h23305b81": {
            "b81": ["education", "health"],
            "b82": {
                "money": "100000 HKD",
                "time": "10 days"
            }
        },
        "h23302c11": {
            "c11": true
        },
        "h23302c21": {
            "c21": true,
            "c22": true
        },
        "h23302c31": {
            "c31": true
        }
    }
}
